iscwatch/__init__.py
iscwatch/logconfig.py
iscwatch/main.py
iscwatch-0.4.0.dist-info/METADATA
iscwatch-0.4.0.dist-info/WHEEL
iscwatch-0.4.0.dist-info/entry_points.txt
iscwatch-0.4.0.dist-info/RECORD
