Metadata-Version: 2.1
Name: iscwatch
Version: 0.4.0
Summary: 
Author: Roger Hurwitz
Author-email: rogerhurwitz@inspirsmith.com
Requires-Python: >=3.11,<4.0
Classifier: Programming Language :: Python :: 3
Classifier: Programming Language :: Python :: 3.11
Requires-Dist: lxml (>=4.9.3,<5.0.0)
Requires-Dist: pandas (>=2.0.3,<3.0.0)
Requires-Dist: typer[all] (>=0.9.0,<0.10.0)
